prowler_mcp_server/__init__.py
prowler_mcp_server/main.py
prowler_mcp_server/server.py
prowler_mcp_server/lib/__init__.py
prowler_mcp_server/lib/logger.py
prowler_mcp_server/prowler_app/__init__.py
prowler_mcp_server/prowler_app/server.py
prowler_mcp_server/prowler_app/models/__init__.py
prowler_mcp_server/prowler_app/models/base.py
prowler_mcp_server/prowler_app/models/compliance.py
prowler_mcp_server/prowler_app/models/findings.py
prowler_mcp_server/prowler_app/models/muting.py
prowler_mcp_server/prowler_app/models/providers.py
prowler_mcp_server/prowler_app/models/resources.py
prowler_mcp_server/prowler_app/models/scans.py
prowler_mcp_server/prowler_app/tools/__init__.py
prowler_mcp_server/prowler_app/tools/base.py
prowler_mcp_server/prowler_app/tools/compliance.py
prowler_mcp_server/prowler_app/tools/findings.py
prowler_mcp_server/prowler_app/tools/muting.py
prowler_mcp_server/prowler_app/tools/providers.py
prowler_mcp_server/prowler_app/tools/resources.py
prowler_mcp_server/prowler_app/tools/scans.py
prowler_mcp_server/prowler_app/utils/api_client.py
prowler_mcp_server/prowler_app/utils/auth.py
prowler_mcp_server/prowler_app/utils/tool_loader.py
prowler_mcp_server/prowler_documentation/__init__.py
prowler_mcp_server/prowler_documentation/search_engine.py
prowler_mcp_server/prowler_documentation/server.py
prowler_mcp_server/prowler_hub/__init__.py
prowler_mcp_server/prowler_hub/server.py
prowler_mcp-0.3.0.dist-info/METADATA
prowler_mcp-0.3.0.dist-info/WHEEL
prowler_mcp-0.3.0.dist-info/entry_points.txt
prowler_mcp-0.3.0.dist-info/top_level.txt
prowler_mcp-0.3.0.dist-info/RECORD
