Metadata-Version: 2.4
Name: prowler-mcp
Version: 0.3.0
Summary: MCP server for Prowler ecosystem
Requires-Python: >=3.12
Requires-Dist: fastmcp==2.14.0
Requires-Dist: httpx>=0.28.0
